unfazed_prometheus/__init__.py
unfazed_prometheus/base.py
unfazed_prometheus/decorators.py
unfazed_prometheus/lifespan.py
unfazed_prometheus/metrics.py
unfazed_prometheus/settings.py
unfazed_prometheus/utils.py
unfazed_prometheus/cache/backends/default.py
unfazed_prometheus/database/tortoise/mysql/__init__.py
unfazed_prometheus/database/tortoise/mysql/base.py
unfazed_prometheus/middleware/common.py
unfazed_prometheus-0.0.2.dist-info/METADATA
unfazed_prometheus-0.0.2.dist-info/WHEEL
unfazed_prometheus-0.0.2.dist-info/licenses/LICENSE
unfazed_prometheus-0.0.2.dist-info/RECORD
