Metadata-Version: 2.4
Name: unfazed-prometheus
Version: 0.0.2
Summary: Prometheus metrics for Unfazed
License-File: LICENSE
Requires-Dist: prometheus-client>=0.21.1
Requires-Dist: unfazed>=0.0.7
